agamotto/__init__.py
agamotto/cron.py
agamotto/file.py
agamotto/group.py
agamotto/network.py
agamotto/nginx.py
agamotto/package.py
agamotto/process.py
agamotto/service.py
agamotto/user.py
agamotto/utils.py
agamotto/version.py
agamotto-0.5.1.dist-info/DESCRIPTION.rst
agamotto-0.5.1.dist-info/METADATA
agamotto-0.5.1.dist-info/metadata.json
agamotto-0.5.1.dist-info/RECORD
agamotto-0.5.1.dist-info/top_level.txt
agamotto-0.5.1.dist-info/WHEEL
