Metadata-Version: 2.0
Name: agamotto
Version: 0.5.1
Summary: Agamotto is a module that provides helper functions for testing the configuration of a running server
Home-page: http://github.com/groksolutions/agamotto
Author: Joe Block
Author-email: jpb@numenta.com
License: Apache
Download-URL: https://github.com/GrokSolutions/agamotto/archive/0.5.1.tar.gz
Keywords: server testing
Platform: UNKNOWN
Classifier: Development Status :: 5 - Production/Stable
Classifier: Intended Audience :: Developers
Classifier: License :: OSI Approved :: Apache Software License
Classifier: Natural Language :: English
Classifier: Operating System :: OS Independent
Classifier: Programming Language :: Python
Requires-Dist: requests
Requires-Dist: unittest2
